smockrawl/__init__.py
smockrawl/__main__.py
smockrawl/smockrawl.py
smockrawl-0.3.0.dist-info/METADATA
smockrawl-0.3.0.dist-info/WHEEL
smockrawl-0.3.0.dist-info/entry_points.txt
smockrawl-0.3.0.dist-info/top_level.txt
smockrawl-0.3.0.dist-info/RECORD
