Metadata-Version: 2.1
Name: smockrawl
Version: 0.3.0
Summary: Smockeo API crawler
Home-page: https://github.com/fedus/smockrawl
Author: Federico Gentile
Author-email: misc+smockrawl@dillendapp.eu
License: UNKNOWN
Keywords: smockeo cobject smoke fire detector api crawl crawler
Platform: UNKNOWN
Classifier: Development Status :: 3 - Alpha
Classifier: Intended Audience :: Developers
Classifier: Topic :: Software Development :: Build Tools
Classifier: License :: OSI Approved :: MIT License
Classifier: Programming Language :: Python :: 3
Requires-Python: >=3.5
Requires-Dist: beautifulsoup4
Requires-Dist: python-dateutil
Requires-Dist: humanfriendly
Requires-Dist: aiohttp
Requires-Dist: async-timeout
